Emu86KernelPYPIDescription.md
MANIFEST.in
README.md
setup.py
assembler/__init__.py
assembler/assemble.py
assembler/errors.py
assembler/flowbreak.py
assembler/lex.py
assembler/ops_check.py
assembler/parse.py
assembler/tokens.py
assembler/virtual_machine.py
assembler/Intel/__init__.py
assembler/Intel/arithmetic.py
assembler/Intel/control_flow.py
assembler/Intel/data_mov.py
assembler/Intel/data_mov_att.py
assembler/Intel/fp_arithmetic.py
assembler/Intel/fp_conversions.py
assembler/Intel/interrupts.py
assembler/Intel/key_words.py
assembler/Intel/math_operations.py
assembler/MIPS/__init__.py
assembler/MIPS/argument_check.py
assembler/MIPS/arithmetic.py
assembler/MIPS/control_flow.py
assembler/MIPS/data_mov.py
assembler/MIPS/fp_arithmetic.py
assembler/MIPS/fp_data_mov.py
assembler/MIPS/interrupts.py
assembler/MIPS/key_words.py
assembler/RISCV/__init__.py
assembler/RISCV/argument_check.py
assembler/RISCV/arithmetic.py
assembler/RISCV/control_flow.py
assembler/RISCV/data_mov.py
assembler/RISCV/interrupts.py
assembler/RISCV/key_words.py
assembler/WASM/__init__.py
assembler/WASM/arithmetic.py
assembler/WASM/data_mov.py
assembler/WASM/key_words.py
emu86.egg-info/PKG-INFO
emu86.egg-info/SOURCES.txt
emu86.egg-info/dependency_links.txt
emu86.egg-info/top_level.txt
kernels/__init__.py
kernels/att/__init__.py
kernels/att/__main__.py
kernels/att/install.py
kernels/att/kernel.py
kernels/att/uninstall.py
kernels/intel/__init__.py
kernels/intel/__main__.py
kernels/intel/install.py
kernels/intel/kernel.py
kernels/intel/uninstall.py
kernels/mips_asm/__init__.py
kernels/mips_asm/__main__.py
kernels/mips_asm/install.py
kernels/mips_asm/kernel.py
kernels/mips_asm/uninstall.py
kernels/mips_mml/__init__.py
kernels/mips_mml/__main__.py
kernels/mips_mml/install.py
kernels/mips_mml/kernel.py
kernels/mips_mml/uninstall.py
kernels/riscv/__init__.py
kernels/riscv/__main__.py
kernels/riscv/install.py
kernels/riscv/kernel.py
kernels/riscv/uninstall.py